<?xml version="1.0" encoding="utf-8"?>
<rdf:RDF xmlns:cim="http://iec.ch/TC57/2010/CIM-schema-cim15#" xmlns:rdf="http://www.w3.org/1999/02/22-rdf-syntax-ns#">
	<cim:SubGeographicalRegion rdf:ID="d2cc2646-de4b-11e6-a64f-02ba7def0216">
		<cim:SubGeographicalRegion.Region rdf:resource="#"/>
	</cim:SubGeographicalRegion>
	<cim:PositionPoint rdf:ID="d2cc2ea2-de4b-11e6-a64f-02ba7def0216">
		<cim:PositionPoint.xPosition>8.61176846913</cim:PositionPoint.xPosition>
		<cim:PositionPoint.zPosition>1</cim:PositionPoint.zPosition>
		<cim:PositionPoint.yPosition>53.5502021848</cim:PositionPoint.yPosition>
		<cim:PositionPoint.Location rdf:resource="#d2cc338e-de4b-11e6-a64f-02ba7def0216"/>
	</cim:PositionPoint>
	<cim:Location rdf:ID="d2cc338e-de4b-11e6-a64f-02ba7def0216"/>
	<cim:PositionPoint rdf:ID="d2cc392e-de4b-11e6-a64f-02ba7def0216">
		<cim:PositionPoint.xPosition>8.62148682555</cim:PositionPoint.xPosition>
		<cim:PositionPoint.yPosition>53.6024955643</cim:PositionPoint.yPosition>
		<cim:PositionPoint.Location rdf:resource="#d2cc3c80-de4b-11e6-a64f-02ba7def0216"/>
	</cim:PositionPoint>
	<cim:Location rdf:ID="d2cc3c80-de4b-11e6-a64f-02ba7def0216"/>
	<cim:Substation rdf:ID="d2cc5530-de4b-11e6-a64f-02ba7def0216">
		<cim:IdentifiedObject.name>SS_41831269</cim:IdentifiedObject.name>
		<cim:PowerSystemResource.Location rdf:resource="#d2cc3c80-de4b-11e6-a64f-02ba7def0216"/>
		<cim:Substation.Region rdf:resource="#d2cc2646-de4b-11e6-a64f-02ba7def0216"/>
	</cim:Substation>
	<cim:PowerTransformer rdf:ID="d2cc5774-de4b-11e6-a64f-02ba7def0216">
		<cim:IdentifiedObject.name>T_41831269_110000_Leherheide</cim:IdentifiedObject.name>
		<cim:Equipment.EquipmentContainer rdf:resource="#d2cc5530-de4b-11e6-a64f-02ba7def0216"/>
	</cim:PowerTransformer>
	<cim:BaseVoltage rdf:ID="d2cc5b2a-de4b-11e6-a64f-02ba7def0216">
		<cim:BaseVoltage.nominalVoltage>110000</cim:BaseVoltage.nominalVoltage>
	</cim:BaseVoltage>
	<cim:TransformerWinding rdf:ID="d2cc6016-de4b-11e6-a64f-02ba7def0216">
		<cim:IdentifiedObject.name>TW_41831269_110000</cim:IdentifiedObject.name>
		<cim:TransformerWinding.x>1.0</cim:TransformerWinding.x>
		<cim:TransformerWinding.ratedS>5000000</cim:TransformerWinding.ratedS>
		<cim:TransformerWinding.r>1.0</cim:TransformerWinding.r>
		<cim:TransformerWinding.ratedU>110000</cim:TransformerWinding.ratedU>
		<cim:TransformerWinding.connectionType rdf:resource="http://iec.ch/TC57/2010/CIM-schema-cim15#WindingConnection.Yn"/>
		<cim:TransformerWinding.windingType rdf:resource="http://iec.ch/TC57/2010/CIM-schema-cim15#WindingType.primary"/>
		<cim:ConductingEquipment.BaseVoltage rdf:resource="#d2cc5b2a-de4b-11e6-a64f-02ba7def0216"/>
		<cim:TransformerWinding.PowerTransformer rdf:resource="#d2cc5774-de4b-11e6-a64f-02ba7def0216"/>
	</cim:TransformerWinding>
	<cim:ConnectivityNode rdf:ID="d2cc62fa-de4b-11e6-a64f-02ba7def0216">
		<cim:IdentifiedObject.name>CN_41831269_110000</cim:IdentifiedObject.name>
	</cim:ConnectivityNode>
	<cim:Terminal rdf:ID="d2cc66a6-de4b-11e6-a64f-02ba7def0216">
		<cim:Terminal.sequenceNumber>1</cim:Terminal.sequenceNumber>
		<cim:Terminal.ConductingEquipment rdf:resource="#d2cc6016-de4b-11e6-a64f-02ba7def0216"/>
		<cim:Terminal.ConnectivityNode rdf:resource="#d2cc62fa-de4b-11e6-a64f-02ba7def0216"/>
	</cim:Terminal>
	<cim:PositionPoint rdf:ID="d2cc6bba-de4b-11e6-a64f-02ba7def0216">
		<cim:PositionPoint.xPosition>8.5380768921</cim:PositionPoint.xPosition>
		<cim:PositionPoint.yPosition>53.5976498561</cim:PositionPoint.yPosition>
		<cim:PositionPoint.Location rdf:resource="#d2cc6ef8-de4b-11e6-a64f-02ba7def0216"/>
	</cim:PositionPoint>
	<cim:Location rdf:ID="d2cc6ef8-de4b-11e6-a64f-02ba7def0216"/>
	<cim:Substation rdf:ID="d2cc790c-de4b-11e6-a64f-02ba7def0216">
		<cim:IdentifiedObject.name>SS_157422539</cim:IdentifiedObject.name>
		<cim:PowerSystemResource.Location rdf:resource="#d2cc6ef8-de4b-11e6-a64f-02ba7def0216"/>
		<cim:Substation.Region rdf:resource="#d2cc2646-de4b-11e6-a64f-02ba7def0216"/>
	</cim:Substation>
	<cim:PowerTransformer rdf:ID="d2cc7b32-de4b-11e6-a64f-02ba7def0216">
		<cim:IdentifiedObject.name>T_157422539_110000_Bremenhaven_Übersehhafen</cim:IdentifiedObject.name>
		<cim:Equipment.EquipmentContainer rdf:resource="#d2cc790c-de4b-11e6-a64f-02ba7def0216"/>
	</cim:PowerTransformer>
	<cim:TransformerWinding rdf:ID="d2cc7f56-de4b-11e6-a64f-02ba7def0216">
		<cim:IdentifiedObject.name>TW_157422539_110000</cim:IdentifiedObject.name>
		<cim:TransformerWinding.x>1.0</cim:TransformerWinding.x>
		<cim:TransformerWinding.ratedS>5000000</cim:TransformerWinding.ratedS>
		<cim:TransformerWinding.r>1.0</cim:TransformerWinding.r>
		<cim:TransformerWinding.ratedU>110000</cim:TransformerWinding.ratedU>
		<cim:TransformerWinding.connectionType rdf:resource="http://iec.ch/TC57/2010/CIM-schema-cim15#WindingConnection.Yn"/>
		<cim:TransformerWinding.windingType rdf:resource="http://iec.ch/TC57/2010/CIM-schema-cim15#WindingType.primary"/>
		<cim:ConductingEquipment.BaseVoltage rdf:resource="#d2cc5b2a-de4b-11e6-a64f-02ba7def0216"/>
		<cim:TransformerWinding.PowerTransformer rdf:resource="#d2cc7b32-de4b-11e6-a64f-02ba7def0216"/>
	</cim:TransformerWinding>
	<cim:ConnectivityNode rdf:ID="d2cc821c-de4b-11e6-a64f-02ba7def0216">
		<cim:IdentifiedObject.name>CN_157422539_110000</cim:IdentifiedObject.name>
	</cim:ConnectivityNode>
	<cim:Terminal rdf:ID="d2cc8528-de4b-11e6-a64f-02ba7def0216">
		<cim:Terminal.sequenceNumber>1</cim:Terminal.sequenceNumber>
		<cim:Terminal.ConductingEquipment rdf:resource="#d2cc7f56-de4b-11e6-a64f-02ba7def0216"/>
		<cim:Terminal.ConnectivityNode rdf:resource="#d2cc821c-de4b-11e6-a64f-02ba7def0216"/>
	</cim:Terminal>
	<cim:PositionPoint rdf:ID="d2ccbdae-de4b-11e6-a64f-02ba7def0216">
		<cim:PositionPoint.xPosition>8.58988909147</cim:PositionPoint.xPosition>
		<cim:PositionPoint.yPosition>53.6102606431</cim:PositionPoint.yPosition>
		<cim:PositionPoint.Location rdf:resource="#d2ccc13c-de4b-11e6-a64f-02ba7def0216"/>
	</cim:PositionPoint>
	<cim:Location rdf:ID="d2ccc13c-de4b-11e6-a64f-02ba7def0216"/>
	<cim:ACLineSegment rdf:ID="d2ccc74a-de4b-11e6-a64f-02ba7def0216">
		<cim:IdentifiedObject.name>_CN_41831269_110000_CN_157422539_110000</cim:IdentifiedObject.name>
		<cim:Conductor.length>9933.90768534</cim:Conductor.length>
		<cim:ACLineSegment.r>0.3257</cim:ACLineSegment.r>
		<cim:ACLineSegment.x0>0.88025</cim:ACLineSegment.x0>
		<cim:ACLineSegment.x>0.3153</cim:ACLineSegment.x>
		<cim:ACLineSegment.r0>0.5336</cim:ACLineSegment.r0>
		<cim:ConductingEquipment.phases rdf:resource="http://iec.ch/TC57/2010/CIM-schema-cim15#PhaseCode.A"/>
		<cim:PowerSystemResource.Location rdf:resource="#d2ccc13c-de4b-11e6-a64f-02ba7def0216"/>
		<cim:ConductingEquipment.BaseVoltage rdf:resource="#d2cc5b2a-de4b-11e6-a64f-02ba7def0216"/>
	</cim:ACLineSegment>
	<cim:Terminal rdf:ID="d2ccca7e-de4b-11e6-a64f-02ba7def0216">
		<cim:Terminal.sequenceNumber>1</cim:Terminal.sequenceNumber>
		<cim:Terminal.ConductingEquipment rdf:resource="#d2ccc74a-de4b-11e6-a64f-02ba7def0216"/>
		<cim:Terminal.ConnectivityNode rdf:resource="#d2cc62fa-de4b-11e6-a64f-02ba7def0216"/>
	</cim:Terminal>
	<cim:Terminal rdf:ID="d2cccda8-de4b-11e6-a64f-02ba7def0216">
		<cim:Terminal.sequenceNumber>2</cim:Terminal.sequenceNumber>
		<cim:Terminal.ConductingEquipment rdf:resource="#d2ccc74a-de4b-11e6-a64f-02ba7def0216"/>
		<cim:Terminal.ConnectivityNode rdf:resource="#d2cc821c-de4b-11e6-a64f-02ba7def0216"/>
	</cim:Terminal>
	<cim:PositionPoint rdf:ID="d2ccd618-de4b-11e6-a64f-02ba7def0216">
		<cim:PositionPoint.xPosition>8.62084769233</cim:PositionPoint.xPosition>
		<cim:PositionPoint.yPosition>53.5109361261</cim:PositionPoint.yPosition>
		<cim:PositionPoint.Location rdf:resource="#d2ccd960-de4b-11e6-a64f-02ba7def0216"/>
	</cim:PositionPoint>
	<cim:Location rdf:ID="d2ccd960-de4b-11e6-a64f-02ba7def0216"/>
	<cim:Substation rdf:ID="d2cce342-de4b-11e6-a64f-02ba7def0216">
		<cim:IdentifiedObject.name>SS_117216153</cim:IdentifiedObject.name>
		<cim:PowerSystemResource.Location rdf:resource="#d2ccd960-de4b-11e6-a64f-02ba7def0216"/>
		<cim:Substation.Region rdf:resource="#d2cc2646-de4b-11e6-a64f-02ba7def0216"/>
	</cim:Substation>
	<cim:PowerTransformer rdf:ID="d2cce568-de4b-11e6-a64f-02ba7def0216">
		<cim:IdentifiedObject.name>T_117216153_110000_Surheide</cim:IdentifiedObject.name>
		<cim:Equipment.EquipmentContainer rdf:resource="#d2cce342-de4b-11e6-a64f-02ba7def0216"/>
	</cim:PowerTransformer>
	<cim:TransformerWinding rdf:ID="d2cce996-de4b-11e6-a64f-02ba7def0216">
		<cim:IdentifiedObject.name>TW_117216153_110000</cim:IdentifiedObject.name>
		<cim:TransformerWinding.x>1.0</cim:TransformerWinding.x>
		<cim:TransformerWinding.ratedS>5000000</cim:TransformerWinding.ratedS>
		<cim:TransformerWinding.r>1.0</cim:TransformerWinding.r>
		<cim:TransformerWinding.ratedU>110000</cim:TransformerWinding.ratedU>
		<cim:TransformerWinding.connectionType rdf:resource="http://iec.ch/TC57/2010/CIM-schema-cim15#WindingConnection.Yn"/>
		<cim:TransformerWinding.windingType rdf:resource="http://iec.ch/TC57/2010/CIM-schema-cim15#WindingType.primary"/>
		<cim:ConductingEquipment.BaseVoltage rdf:resource="#d2cc5b2a-de4b-11e6-a64f-02ba7def0216"/>
		<cim:TransformerWinding.PowerTransformer rdf:resource="#d2cce568-de4b-11e6-a64f-02ba7def0216"/>
	</cim:TransformerWinding>
	<cim:ConnectivityNode rdf:ID="d2ccec5c-de4b-11e6-a64f-02ba7def0216">
		<cim:IdentifiedObject.name>CN_117216153_110000</cim:IdentifiedObject.name>
	</cim:ConnectivityNode>
	<cim:Terminal rdf:ID="d2ccef68-de4b-11e6-a64f-02ba7def0216">
		<cim:Terminal.sequenceNumber>1</cim:Terminal.sequenceNumber>
		<cim:Terminal.ConductingEquipment rdf:resource="#d2cce996-de4b-11e6-a64f-02ba7def0216"/>
		<cim:Terminal.ConnectivityNode rdf:resource="#d2ccec5c-de4b-11e6-a64f-02ba7def0216"/>
	</cim:Terminal>
	<cim:PositionPoint rdf:ID="d2cd311c-de4b-11e6-a64f-02ba7def0216">
		<cim:PositionPoint.xPosition>8.64142839299</cim:PositionPoint.xPosition>
		<cim:PositionPoint.yPosition>53.5652055772</cim:PositionPoint.yPosition>
		<cim:PositionPoint.Location rdf:resource="#d2cd34b4-de4b-11e6-a64f-02ba7def0216"/>
	</cim:PositionPoint>
	<cim:Location rdf:ID="d2cd34b4-de4b-11e6-a64f-02ba7def0216"/>
	<cim:ACLineSegment rdf:ID="d2cd3a4a-de4b-11e6-a64f-02ba7def0216">
		<cim:IdentifiedObject.name>_CN_41831269_110000_CN_117216153_110000</cim:IdentifiedObject.name>
		<cim:Conductor.length>13659.7237111</cim:Conductor.length>
		<cim:ACLineSegment.r>0.3257</cim:ACLineSegment.r>
		<cim:ACLineSegment.x0>0.88025</cim:ACLineSegment.x0>
		<cim:ACLineSegment.x>0.3153</cim:ACLineSegment.x>
		<cim:ACLineSegment.r0>0.5336</cim:ACLineSegment.r0>
		<cim:ConductingEquipment.phases rdf:resource="http://iec.ch/TC57/2010/CIM-schema-cim15#PhaseCode.A"/>
		<cim:PowerSystemResource.Location rdf:resource="#d2cd34b4-de4b-11e6-a64f-02ba7def0216"/>
		<cim:ConductingEquipment.BaseVoltage rdf:resource="#d2cc5b2a-de4b-11e6-a64f-02ba7def0216"/>
	</cim:ACLineSegment>
	<cim:Terminal rdf:ID="d2cd3d88-de4b-11e6-a64f-02ba7def0216">
		<cim:Terminal.sequenceNumber>1</cim:Terminal.sequenceNumber>
		<cim:Terminal.ConductingEquipment rdf:resource="#d2cd3a4a-de4b-11e6-a64f-02ba7def0216"/>
		<cim:Terminal.ConnectivityNode rdf:resource="#d2cc62fa-de4b-11e6-a64f-02ba7def0216"/>
	</cim:Terminal>
	<cim:Terminal rdf:ID="d2cd408a-de4b-11e6-a64f-02ba7def0216">
		<cim:Terminal.sequenceNumber>2</cim:Terminal.sequenceNumber>
		<cim:Terminal.ConductingEquipment rdf:resource="#d2cd3a4a-de4b-11e6-a64f-02ba7def0216"/>
		<cim:Terminal.ConnectivityNode rdf:resource="#d2ccec5c-de4b-11e6-a64f-02ba7def0216"/>
	</cim:Terminal>
	<cim:PositionPoint rdf:ID="d2cd48d2-de4b-11e6-a64f-02ba7def0216">
		<cim:PositionPoint.xPosition>8.60137576609</cim:PositionPoint.xPosition>
		<cim:PositionPoint.yPosition>53.5601422659</cim:PositionPoint.yPosition>
		<cim:PositionPoint.Location rdf:resource="#d2cd4c10-de4b-11e6-a64f-02ba7def0216"/>
	</cim:PositionPoint>
	<cim:Location rdf:ID="d2cd4c10-de4b-11e6-a64f-02ba7def0216"/>
	<cim:Substation rdf:ID="d2cd55ac-de4b-11e6-a64f-02ba7def0216">
		<cim:IdentifiedObject.name>SS_111990696</cim:IdentifiedObject.name>
		<cim:PowerSystemResource.Location rdf:resource="#d2cd4c10-de4b-11e6-a64f-02ba7def0216"/>
		<cim:Substation.Region rdf:resource="#d2cc2646-de4b-11e6-a64f-02ba7def0216"/>
	</cim:Substation>
	<cim:PowerTransformer rdf:ID="d2cd57c8-de4b-11e6-a64f-02ba7def0216">
		<cim:IdentifiedObject.name>T_111990696_110000_</cim:IdentifiedObject.name>
		<cim:Equipment.EquipmentContainer rdf:resource="#d2cd55ac-de4b-11e6-a64f-02ba7def0216"/>
	</cim:PowerTransformer>
	<cim:TransformerWinding rdf:ID="d2cd5bf6-de4b-11e6-a64f-02ba7def0216">
		<cim:IdentifiedObject.name>TW_111990696_110000</cim:IdentifiedObject.name>
		<cim:TransformerWinding.x>1.0</cim:TransformerWinding.x>
		<cim:TransformerWinding.ratedS>5000000</cim:TransformerWinding.ratedS>
		<cim:TransformerWinding.r>1.0</cim:TransformerWinding.r>
		<cim:TransformerWinding.ratedU>110000</cim:TransformerWinding.ratedU>
		<cim:TransformerWinding.connectionType rdf:resource="http://iec.ch/TC57/2010/CIM-schema-cim15#WindingConnection.Yn"/>
		<cim:TransformerWinding.windingType rdf:resource="http://iec.ch/TC57/2010/CIM-schema-cim15#WindingType.primary"/>
		<cim:ConductingEquipment.BaseVoltage rdf:resource="#d2cc5b2a-de4b-11e6-a64f-02ba7def0216"/>
		<cim:TransformerWinding.PowerTransformer rdf:resource="#d2cd57c8-de4b-11e6-a64f-02ba7def0216"/>
	</cim:TransformerWinding>
	<cim:ConnectivityNode rdf:ID="d2cd5ebc-de4b-11e6-a64f-02ba7def0216">
		<cim:IdentifiedObject.name>CN_111990696_110000</cim:IdentifiedObject.name>
	</cim:ConnectivityNode>
	<cim:Terminal rdf:ID="d2cd61be-de4b-11e6-a64f-02ba7def0216">
		<cim:Terminal.sequenceNumber>1</cim:Terminal.sequenceNumber>
		<cim:Terminal.ConductingEquipment rdf:resource="#d2cd5bf6-de4b-11e6-a64f-02ba7def0216"/>
		<cim:Terminal.ConnectivityNode rdf:resource="#d2cd5ebc-de4b-11e6-a64f-02ba7def0216"/>
	</cim:Terminal>
	<cim:PositionPoint rdf:ID="d2cd9846-de4b-11e6-a64f-02ba7def0216">
		<cim:PositionPoint.xPosition>8.63798344444</cim:PositionPoint.xPosition>
		<cim:PositionPoint.yPosition>53.5810840128</cim:PositionPoint.yPosition>
		<cim:PositionPoint.Location rdf:resource="#d2cd9bb6-de4b-11e6-a64f-02ba7def0216"/>
	</cim:PositionPoint>
	<cim:Location rdf:ID="d2cd9bb6-de4b-11e6-a64f-02ba7def0216"/>
	<cim:ACLineSegment rdf:ID="d2cda016-de4b-11e6-a64f-02ba7def0216">
		<cim:IdentifiedObject.name>_CN_41831269_110000_CN_111990696_110000</cim:IdentifiedObject.name>
		<cim:Conductor.length>10125.47039</cim:Conductor.length>
		<cim:ACLineSegment.r>0.3257</cim:ACLineSegment.r>
		<cim:ACLineSegment.x0>0.88025</cim:ACLineSegment.x0>
		<cim:ACLineSegment.x>0.3153</cim:ACLineSegment.x>
		<cim:ACLineSegment.r0>0.5336</cim:ACLineSegment.r0>
		<cim:ConductingEquipment.phases rdf:resource="http://iec.ch/TC57/2010/CIM-schema-cim15#PhaseCode.A"/>
		<cim:PowerSystemResource.Location rdf:resource="#d2cd9bb6-de4b-11e6-a64f-02ba7def0216"/>
		<cim:ConductingEquipment.BaseVoltage rdf:resource="#d2cc5b2a-de4b-11e6-a64f-02ba7def0216"/>
	</cim:ACLineSegment>
	<cim:Terminal rdf:ID="d2cda340-de4b-11e6-a64f-02ba7def0216">
		<cim:Terminal.sequenceNumber>1</cim:Terminal.sequenceNumber>
		<cim:Terminal.ConductingEquipment rdf:resource="#d2cda016-de4b-11e6-a64f-02ba7def0216"/>
		<cim:Terminal.ConnectivityNode rdf:resource="#d2cc62fa-de4b-11e6-a64f-02ba7def0216"/>
	</cim:Terminal>
	<cim:Terminal rdf:ID="d2cda638-de4b-11e6-a64f-02ba7def0216">
		<cim:Terminal.sequenceNumber>2</cim:Terminal.sequenceNumber>
		<cim:Terminal.ConductingEquipment rdf:resource="#d2cda016-de4b-11e6-a64f-02ba7def0216"/>
		<cim:Terminal.ConnectivityNode rdf:resource="#d2cd5ebc-de4b-11e6-a64f-02ba7def0216"/>
	</cim:Terminal>
	<cim:PositionPoint rdf:ID="d2cddac2-de4b-11e6-a64f-02ba7def0216">
		<cim:PositionPoint.xPosition>8.62244478458</cim:PositionPoint.xPosition>
		<cim:PositionPoint.yPosition>53.5436115902</cim:PositionPoint.yPosition>
		<cim:PositionPoint.Location rdf:resource="#d2cdde46-de4b-11e6-a64f-02ba7def0216"/>
	</cim:PositionPoint>
	<cim:Location rdf:ID="d2cdde46-de4b-11e6-a64f-02ba7def0216"/>
	<cim:ACLineSegment rdf:ID="d2cde2ba-de4b-11e6-a64f-02ba7def0216">
		<cim:IdentifiedObject.name>_CN_111990696_110000_CN_117216153_110000</cim:IdentifiedObject.name>
		<cim:Conductor.length>7722.89493038</cim:Conductor.length>
		<cim:ACLineSegment.r>0.3257</cim:ACLineSegment.r>
		<cim:ACLineSegment.x0>0.88025</cim:ACLineSegment.x0>
		<cim:ACLineSegment.x>0.3153</cim:ACLineSegment.x>
		<cim:ACLineSegment.r0>0.5336</cim:ACLineSegment.r0>
		<cim:ConductingEquipment.phases rdf:resource="http://iec.ch/TC57/2010/CIM-schema-cim15#PhaseCode.A"/>
		<cim:PowerSystemResource.Location rdf:resource="#d2cdde46-de4b-11e6-a64f-02ba7def0216"/>
		<cim:ConductingEquipment.BaseVoltage rdf:resource="#d2cc5b2a-de4b-11e6-a64f-02ba7def0216"/>
	</cim:ACLineSegment>
	<cim:Terminal rdf:ID="d2cde5e4-de4b-11e6-a64f-02ba7def0216">
		<cim:Terminal.sequenceNumber>1</cim:Terminal.sequenceNumber>
		<cim:Terminal.ConductingEquipment rdf:resource="#d2cde2ba-de4b-11e6-a64f-02ba7def0216"/>
		<cim:Terminal.ConnectivityNode rdf:resource="#d2cd5ebc-de4b-11e6-a64f-02ba7def0216"/>
	</cim:Terminal>
	<cim:Terminal rdf:ID="d2cde92c-de4b-11e6-a64f-02ba7def0216">
		<cim:Terminal.sequenceNumber>2</cim:Terminal.sequenceNumber>
		<cim:Terminal.ConductingEquipment rdf:resource="#d2cde2ba-de4b-11e6-a64f-02ba7def0216"/>
		<cim:Terminal.ConnectivityNode rdf:resource="#d2ccec5c-de4b-11e6-a64f-02ba7def0216"/>
	</cim:Terminal>
	<cim:PositionPoint rdf:ID="d2cdf1a6-de4b-11e6-a64f-02ba7def0216">
		<cim:PositionPoint.xPosition>8.59479173276</cim:PositionPoint.xPosition>
		<cim:PositionPoint.yPosition>53.50091293</cim:PositionPoint.yPosition>
		<cim:PositionPoint.Location rdf:resource="#d2cdf4e4-de4b-11e6-a64f-02ba7def0216"/>
	</cim:PositionPoint>
	<cim:Location rdf:ID="d2cdf4e4-de4b-11e6-a64f-02ba7def0216"/>
	<cim:Substation rdf:ID="d2cdff0c-de4b-11e6-a64f-02ba7def0216">
		<cim:IdentifiedObject.name>SS_370348954</cim:IdentifiedObject.name>
		<cim:PowerSystemResource.Location rdf:resource="#d2cdf4e4-de4b-11e6-a64f-02ba7def0216"/>
		<cim:Substation.Region rdf:resource="#d2cc2646-de4b-11e6-a64f-02ba7def0216"/>
	</cim:Substation>
	<cim:PowerTransformer rdf:ID="d2ce013c-de4b-11e6-a64f-02ba7def0216">
		<cim:IdentifiedObject.name>T_370348954_110000_Wulsdorf</cim:IdentifiedObject.name>
		<cim:Equipment.EquipmentContainer rdf:resource="#d2cdff0c-de4b-11e6-a64f-02ba7def0216"/>
	</cim:PowerTransformer>
	<cim:TransformerWinding rdf:ID="d2ce057e-de4b-11e6-a64f-02ba7def0216">
		<cim:IdentifiedObject.name>TW_370348954_110000</cim:IdentifiedObject.name>
		<cim:TransformerWinding.x>1.0</cim:TransformerWinding.x>
		<cim:TransformerWinding.ratedS>5000000</cim:TransformerWinding.ratedS>
		<cim:TransformerWinding.r>1.0</cim:TransformerWinding.r>
		<cim:TransformerWinding.ratedU>110000</cim:TransformerWinding.ratedU>
		<cim:TransformerWinding.connectionType rdf:resource="http://iec.ch/TC57/2010/CIM-schema-cim15#WindingConnection.Yn"/>
		<cim:TransformerWinding.windingType rdf:resource="http://iec.ch/TC57/2010/CIM-schema-cim15#WindingType.primary"/>
		<cim:ConductingEquipment.BaseVoltage rdf:resource="#d2cc5b2a-de4b-11e6-a64f-02ba7def0216"/>
		<cim:TransformerWinding.PowerTransformer rdf:resource="#d2ce013c-de4b-11e6-a64f-02ba7def0216"/>
	</cim:TransformerWinding>
	<cim:ConnectivityNode rdf:ID="d2ce0844-de4b-11e6-a64f-02ba7def0216">
		<cim:IdentifiedObject.name>CN_370348954_110000</cim:IdentifiedObject.name>
	</cim:ConnectivityNode>
	<cim:Terminal rdf:ID="d2ce0b46-de4b-11e6-a64f-02ba7def0216">
		<cim:Terminal.sequenceNumber>1</cim:Terminal.sequenceNumber>
		<cim:Terminal.ConductingEquipment rdf:resource="#d2ce057e-de4b-11e6-a64f-02ba7def0216"/>
		<cim:Terminal.ConnectivityNode rdf:resource="#d2ce0844-de4b-11e6-a64f-02ba7def0216"/>
	</cim:Terminal>
	<cim:PositionPoint rdf:ID="d2ce3954-de4b-11e6-a64f-02ba7def0216">
		<cim:PositionPoint.xPosition>8.61190920529</cim:PositionPoint.xPosition>
		<cim:PositionPoint.yPosition>53.4987200515</cim:PositionPoint.yPosition>
		<cim:PositionPoint.Location rdf:resource="#d2ce3cc4-de4b-11e6-a64f-02ba7def0216"/>
	</cim:PositionPoint>
	<cim:Location rdf:ID="d2ce3cc4-de4b-11e6-a64f-02ba7def0216"/>
	<cim:ACLineSegment rdf:ID="d2ce4138-de4b-11e6-a64f-02ba7def0216">
		<cim:IdentifiedObject.name>_CN_117216153_110000_CN_370348954_110000</cim:IdentifiedObject.name>
		<cim:Conductor.length>4456.87075974</cim:Conductor.length>
		<cim:ACLineSegment.r>0.3257</cim:ACLineSegment.r>
		<cim:ACLineSegment.x0>0.88025</cim:ACLineSegment.x0>
		<cim:ACLineSegment.x>0.3153</cim:ACLineSegment.x>
		<cim:ACLineSegment.r0>0.5336</cim:ACLineSegment.r0>
		<cim:ConductingEquipment.phases rdf:resource="http://iec.ch/TC57/2010/CIM-schema-cim15#PhaseCode.A"/>
		<cim:PowerSystemResource.Location rdf:resource="#d2ce3cc4-de4b-11e6-a64f-02ba7def0216"/>
		<cim:ConductingEquipment.BaseVoltage rdf:resource="#d2cc5b2a-de4b-11e6-a64f-02ba7def0216"/>
	</cim:ACLineSegment>
	<cim:Terminal rdf:ID="d2ce4462-de4b-11e6-a64f-02ba7def0216">
		<cim:Terminal.sequenceNumber>1</cim:Terminal.sequenceNumber>
		<cim:Terminal.ConductingEquipment rdf:resource="#d2ce4138-de4b-11e6-a64f-02ba7def0216"/>
		<cim:Terminal.ConnectivityNode rdf:resource="#d2ccec5c-de4b-11e6-a64f-02ba7def0216"/>
	</cim:Terminal>
	<cim:Terminal rdf:ID="d2ce4764-de4b-11e6-a64f-02ba7def0216">
		<cim:Terminal.sequenceNumber>2</cim:Terminal.sequenceNumber>
		<cim:Terminal.ConductingEquipment rdf:resource="#d2ce4138-de4b-11e6-a64f-02ba7def0216"/>
		<cim:Terminal.ConnectivityNode rdf:resource="#d2ce0844-de4b-11e6-a64f-02ba7def0216"/>
	</cim:Terminal>
	<cim:PositionPoint rdf:ID="d2ce4f8e-de4b-11e6-a64f-02ba7def0216">
		<cim:PositionPoint.xPosition>8.60253274888</cim:PositionPoint.xPosition>
		<cim:PositionPoint.yPosition>53.5156399836</cim:PositionPoint.yPosition>
		<cim:PositionPoint.Location rdf:resource="#d2ce52d6-de4b-11e6-a64f-02ba7def0216"/>
	</cim:PositionPoint>
	<cim:Location rdf:ID="d2ce52d6-de4b-11e6-a64f-02ba7def0216"/>
	<cim:Substation rdf:ID="d2ce5ca4-de4b-11e6-a64f-02ba7def0216">
		<cim:IdentifiedObject.name>SS_36903323</cim:IdentifiedObject.name>
		<cim:PowerSystemResource.Location rdf:resource="#d2ce52d6-de4b-11e6-a64f-02ba7def0216"/>
		<cim:Substation.Region rdf:resource="#d2cc2646-de4b-11e6-a64f-02ba7def0216"/>
	</cim:Substation>
	<cim:PowerTransformer rdf:ID="d2ce5ec0-de4b-11e6-a64f-02ba7def0216">
		<cim:IdentifiedObject.name>T_36903323_110000_Wulsdorf</cim:IdentifiedObject.name>
		<cim:Equipment.EquipmentContainer rdf:resource="#d2ce5ca4-de4b-11e6-a64f-02ba7def0216"/>
	</cim:PowerTransformer>
	<cim:TransformerWinding rdf:ID="d2ce6302-de4b-11e6-a64f-02ba7def0216">
		<cim:IdentifiedObject.name>TW_36903323_110000</cim:IdentifiedObject.name>
		<cim:TransformerWinding.x>1.0</cim:TransformerWinding.x>
		<cim:TransformerWinding.ratedS>5000000</cim:TransformerWinding.ratedS>
		<cim:TransformerWinding.r>1.0</cim:TransformerWinding.r>
		<cim:TransformerWinding.ratedU>110000</cim:TransformerWinding.ratedU>
		<cim:TransformerWinding.connectionType rdf:resource="http://iec.ch/TC57/2010/CIM-schema-cim15#WindingConnection.Yn"/>
		<cim:TransformerWinding.windingType rdf:resource="http://iec.ch/TC57/2010/CIM-schema-cim15#WindingType.primary"/>
		<cim:ConductingEquipment.BaseVoltage rdf:resource="#d2cc5b2a-de4b-11e6-a64f-02ba7def0216"/>
		<cim:TransformerWinding.PowerTransformer rdf:resource="#d2ce5ec0-de4b-11e6-a64f-02ba7def0216"/>
	</cim:TransformerWinding>
	<cim:ConnectivityNode rdf:ID="d2ce65be-de4b-11e6-a64f-02ba7def0216">
		<cim:IdentifiedObject.name>CN_36903323_110000</cim:IdentifiedObject.name>
	</cim:ConnectivityNode>
	<cim:Terminal rdf:ID="d2ce68ca-de4b-11e6-a64f-02ba7def0216">
		<cim:Terminal.sequenceNumber>1</cim:Terminal.sequenceNumber>
		<cim:Terminal.ConductingEquipment rdf:resource="#d2ce6302-de4b-11e6-a64f-02ba7def0216"/>
		<cim:Terminal.ConnectivityNode rdf:resource="#d2ce65be-de4b-11e6-a64f-02ba7def0216"/>
	</cim:Terminal>
	<cim:PositionPoint rdf:ID="d2ce93cc-de4b-11e6-a64f-02ba7def0216">
		<cim:PositionPoint.xPosition>8.61227201856</cim:PositionPoint.xPosition>
		<cim:PositionPoint.yPosition>53.5137760257</cim:PositionPoint.yPosition>
		<cim:PositionPoint.Location rdf:resource="#d2ce973c-de4b-11e6-a64f-02ba7def0216"/>
	</cim:PositionPoint>
	<cim:Location rdf:ID="d2ce973c-de4b-11e6-a64f-02ba7def0216"/>
	<cim:ACLineSegment rdf:ID="d2ce9bb0-de4b-11e6-a64f-02ba7def0216">
		<cim:IdentifiedObject.name>_CN_117216153_110000_CN_36903323_110000</cim:IdentifiedObject.name>
		<cim:Conductor.length>1305.67648895</cim:Conductor.length>
		<cim:ACLineSegment.r>0.3257</cim:ACLineSegment.r>
		<cim:ACLineSegment.x0>0.88025</cim:ACLineSegment.x0>
		<cim:ACLineSegment.x>0.3153</cim:ACLineSegment.x>
		<cim:ACLineSegment.r0>0.5336</cim:ACLineSegment.r0>
		<cim:ConductingEquipment.phases rdf:resource="http://iec.ch/TC57/2010/CIM-schema-cim15#PhaseCode.A"/>
		<cim:PowerSystemResource.Location rdf:resource="#d2ce973c-de4b-11e6-a64f-02ba7def0216"/>
		<cim:ConductingEquipment.BaseVoltage rdf:resource="#d2cc5b2a-de4b-11e6-a64f-02ba7def0216"/>
	</cim:ACLineSegment>
	<cim:Terminal rdf:ID="d2ce9eda-de4b-11e6-a64f-02ba7def0216">
		<cim:Terminal.sequenceNumber>1</cim:Terminal.sequenceNumber>
		<cim:Terminal.ConductingEquipment rdf:resource="#d2ce9bb0-de4b-11e6-a64f-02ba7def0216"/>
		<cim:Terminal.ConnectivityNode rdf:resource="#d2ccec5c-de4b-11e6-a64f-02ba7def0216"/>
	</cim:Terminal>
	<cim:Terminal rdf:ID="d2cea1e6-de4b-11e6-a64f-02ba7def0216">
		<cim:Terminal.sequenceNumber>2</cim:Terminal.sequenceNumber>
		<cim:Terminal.ConductingEquipment rdf:resource="#d2ce9bb0-de4b-11e6-a64f-02ba7def0216"/>
		<cim:Terminal.ConnectivityNode rdf:resource="#d2ce65be-de4b-11e6-a64f-02ba7def0216"/>
	</cim:Terminal>
	<cim:TransformerWinding rdf:ID="d2cea858-de4b-11e6-a64f-02ba7def0216">
		<cim:IdentifiedObject.name>TW_41831269_110000</cim:IdentifiedObject.name>
		<cim:TransformerWinding.x>1.0</cim:TransformerWinding.x>
		<cim:TransformerWinding.ratedS>5000000</cim:TransformerWinding.ratedS>
		<cim:TransformerWinding.r>1.0</cim:TransformerWinding.r>
		<cim:TransformerWinding.ratedU>110000</cim:TransformerWinding.ratedU>
		<cim:TransformerWinding.connectionType rdf:resource="http://iec.ch/TC57/2010/CIM-schema-cim15#WindingConnection.Yn"/>
		<cim:TransformerWinding.windingType rdf:resource="http://iec.ch/TC57/2010/CIM-schema-cim15#WindingType.secondary"/>
		<cim:ConductingEquipment.BaseVoltage rdf:resource="#d2cc5b2a-de4b-11e6-a64f-02ba7def0216"/>
		<cim:TransformerWinding.PowerTransformer rdf:resource="#d2cc5774-de4b-11e6-a64f-02ba7def0216"/>
	</cim:TransformerWinding>
	<cim:ConnectivityNode rdf:ID="d2ceab32-de4b-11e6-a64f-02ba7def0216">
		<cim:IdentifiedObject.name>CN_41831269_110000</cim:IdentifiedObject.name>
	</cim:ConnectivityNode>
	<cim:Terminal rdf:ID="d2ceae2a-de4b-11e6-a64f-02ba7def0216">
		<cim:Terminal.sequenceNumber>1</cim:Terminal.sequenceNumber>
		<cim:Terminal.ConductingEquipment rdf:resource="#d2cea858-de4b-11e6-a64f-02ba7def0216"/>
		<cim:Terminal.ConnectivityNode rdf:resource="#d2ceab32-de4b-11e6-a64f-02ba7def0216"/>
	</cim:Terminal>
	<cim:LoadResponseCharacteristic rdf:ID="d2ceb172-de4b-11e6-a64f-02ba7def0216">
		<cim:LoadResponseCharacteristic.pConstantPower>100000</cim:LoadResponseCharacteristic.pConstantPower>
	</cim:LoadResponseCharacteristic>
	<cim:EnergyConsumer rdf:ID="d2cec216-de4b-11e6-a64f-02ba7def0216">
		<cim:IdentifiedObject.name>L_41831269</cim:IdentifiedObject.name>
		<cim:ConductingEquipment.phases rdf:resource="http://iec.ch/TC57/2010/CIM-schema-cim15#PhaseCode.A"/>
		<cim:ConductingEquipment.BaseVoltage rdf:resource="#d2cc5b2a-de4b-11e6-a64f-02ba7def0216"/>
		<cim:EnergyConsumer.LoadResponse rdf:resource="#d2ceb172-de4b-11e6-a64f-02ba7def0216"/>
	</cim:EnergyConsumer>
	<cim:Terminal rdf:ID="d2cec586-de4b-11e6-a64f-02ba7def0216">
		<cim:Terminal.sequenceNumber>1</cim:Terminal.sequenceNumber>
		<cim:Terminal.ConductingEquipment rdf:resource="#d2cec216-de4b-11e6-a64f-02ba7def0216"/>
		<cim:Terminal.ConnectivityNode rdf:resource="#d2ceab32-de4b-11e6-a64f-02ba7def0216"/>
	</cim:Terminal>
	<cim:TransformerWinding rdf:ID="d2ceca0e-de4b-11e6-a64f-02ba7def0216">
		<cim:IdentifiedObject.name>TW_157422539_110000</cim:IdentifiedObject.name>
		<cim:TransformerWinding.x>1.0</cim:TransformerWinding.x>
		<cim:TransformerWinding.ratedS>5000000</cim:TransformerWinding.ratedS>
		<cim:TransformerWinding.r>1.0</cim:TransformerWinding.r>
		<cim:TransformerWinding.ratedU>110000</cim:TransformerWinding.ratedU>
		<cim:TransformerWinding.connectionType rdf:resource="http://iec.ch/TC57/2010/CIM-schema-cim15#WindingConnection.Yn"/>
		<cim:TransformerWinding.windingType rdf:resource="http://iec.ch/TC57/2010/CIM-schema-cim15#WindingType.secondary"/>
		<cim:ConductingEquipment.BaseVoltage rdf:resource="#d2cc5b2a-de4b-11e6-a64f-02ba7def0216"/>
		<cim:TransformerWinding.PowerTransformer rdf:resource="#d2cc7b32-de4b-11e6-a64f-02ba7def0216"/>
	</cim:TransformerWinding>
	<cim:ConnectivityNode rdf:ID="d2ceccd4-de4b-11e6-a64f-02ba7def0216">
		<cim:IdentifiedObject.name>CN_157422539_110000</cim:IdentifiedObject.name>
	</cim:ConnectivityNode>
	<cim:Terminal rdf:ID="d2cecfd6-de4b-11e6-a64f-02ba7def0216">
		<cim:Terminal.sequenceNumber>1</cim:Terminal.sequenceNumber>
		<cim:Terminal.ConductingEquipment rdf:resource="#d2ceca0e-de4b-11e6-a64f-02ba7def0216"/>
		<cim:Terminal.ConnectivityNode rdf:resource="#d2ceccd4-de4b-11e6-a64f-02ba7def0216"/>
	</cim:Terminal>
	<cim:LoadResponseCharacteristic rdf:ID="d2ced288-de4b-11e6-a64f-02ba7def0216">
		<cim:LoadResponseCharacteristic.pConstantPower>100000</cim:LoadResponseCharacteristic.pConstantPower>
	</cim:LoadResponseCharacteristic>
	<cim:EnergyConsumer rdf:ID="d2ced6ca-de4b-11e6-a64f-02ba7def0216">
		<cim:IdentifiedObject.name>L_157422539</cim:IdentifiedObject.name>
		<cim:ConductingEquipment.phases rdf:resource="http://iec.ch/TC57/2010/CIM-schema-cim15#PhaseCode.A"/>
		<cim:ConductingEquipment.BaseVoltage rdf:resource="#d2cc5b2a-de4b-11e6-a64f-02ba7def0216"/>
		<cim:EnergyConsumer.LoadResponse rdf:resource="#d2ced288-de4b-11e6-a64f-02ba7def0216"/>
	</cim:EnergyConsumer>
	<cim:Terminal rdf:ID="d2ceda58-de4b-11e6-a64f-02ba7def0216">
		<cim:Terminal.sequenceNumber>1</cim:Terminal.sequenceNumber>
		<cim:Terminal.ConductingEquipment rdf:resource="#d2ced6ca-de4b-11e6-a64f-02ba7def0216"/>
		<cim:Terminal.ConnectivityNode rdf:resource="#d2ceccd4-de4b-11e6-a64f-02ba7def0216"/>
	</cim:Terminal>
	<cim:TransformerWinding rdf:ID="d2cedecc-de4b-11e6-a64f-02ba7def0216">
		<cim:IdentifiedObject.name>TW_117216153_110000</cim:IdentifiedObject.name>
		<cim:TransformerWinding.x>1.0</cim:TransformerWinding.x>
		<cim:TransformerWinding.ratedS>5000000</cim:TransformerWinding.ratedS>
		<cim:TransformerWinding.r>1.0</cim:TransformerWinding.r>
		<cim:TransformerWinding.ratedU>110000</cim:TransformerWinding.ratedU>
		<cim:TransformerWinding.connectionType rdf:resource="http://iec.ch/TC57/2010/CIM-schema-cim15#WindingConnection.Yn"/>
		<cim:TransformerWinding.windingType rdf:resource="http://iec.ch/TC57/2010/CIM-schema-cim15#WindingType.secondary"/>
		<cim:ConductingEquipment.BaseVoltage rdf:resource="#d2cc5b2a-de4b-11e6-a64f-02ba7def0216"/>
		<cim:TransformerWinding.PowerTransformer rdf:resource="#d2cce568-de4b-11e6-a64f-02ba7def0216"/>
	</cim:TransformerWinding>
	<cim:ConnectivityNode rdf:ID="d2cee192-de4b-11e6-a64f-02ba7def0216">
		<cim:IdentifiedObject.name>CN_117216153_110000</cim:IdentifiedObject.name>
	</cim:ConnectivityNode>
	<cim:Terminal rdf:ID="d2cee480-de4b-11e6-a64f-02ba7def0216">
		<cim:Terminal.sequenceNumber>1</cim:Terminal.sequenceNumber>
		<cim:Terminal.ConductingEquipment rdf:resource="#d2cedecc-de4b-11e6-a64f-02ba7def0216"/>
		<cim:Terminal.ConnectivityNode rdf:resource="#d2cee192-de4b-11e6-a64f-02ba7def0216"/>
	</cim:Terminal>
	<cim:LoadResponseCharacteristic rdf:ID="d2cee732-de4b-11e6-a64f-02ba7def0216">
		<cim:LoadResponseCharacteristic.pConstantPower>100000</cim:LoadResponseCharacteristic.pConstantPower>
	</cim:LoadResponseCharacteristic>
	<cim:EnergyConsumer rdf:ID="d2ceeb56-de4b-11e6-a64f-02ba7def0216">
		<cim:IdentifiedObject.name>L_117216153</cim:IdentifiedObject.name>
		<cim:ConductingEquipment.phases rdf:resource="http://iec.ch/TC57/2010/CIM-schema-cim15#PhaseCode.A"/>
		<cim:ConductingEquipment.BaseVoltage rdf:resource="#d2cc5b2a-de4b-11e6-a64f-02ba7def0216"/>
		<cim:EnergyConsumer.LoadResponse rdf:resource="#d2cee732-de4b-11e6-a64f-02ba7def0216"/>
	</cim:EnergyConsumer>
	<cim:Terminal rdf:ID="d2ceee80-de4b-11e6-a64f-02ba7def0216">
		<cim:Terminal.sequenceNumber>1</cim:Terminal.sequenceNumber>
		<cim:Terminal.ConductingEquipment rdf:resource="#d2ceeb56-de4b-11e6-a64f-02ba7def0216"/>
		<cim:Terminal.ConnectivityNode rdf:resource="#d2cee192-de4b-11e6-a64f-02ba7def0216"/>
	</cim:Terminal>
	<cim:TransformerWinding rdf:ID="d2cef2d6-de4b-11e6-a64f-02ba7def0216">
		<cim:IdentifiedObject.name>TW_111990696_110000</cim:IdentifiedObject.name>
		<cim:TransformerWinding.x>1.0</cim:TransformerWinding.x>
		<cim:TransformerWinding.ratedS>5000000</cim:TransformerWinding.ratedS>
		<cim:TransformerWinding.r>1.0</cim:TransformerWinding.r>
		<cim:TransformerWinding.ratedU>110000</cim:TransformerWinding.ratedU>
		<cim:TransformerWinding.connectionType rdf:resource="http://iec.ch/TC57/2010/CIM-schema-cim15#WindingConnection.Yn"/>
		<cim:TransformerWinding.windingType rdf:resource="http://iec.ch/TC57/2010/CIM-schema-cim15#WindingType.secondary"/>
		<cim:ConductingEquipment.BaseVoltage rdf:resource="#d2cc5b2a-de4b-11e6-a64f-02ba7def0216"/>
		<cim:TransformerWinding.PowerTransformer rdf:resource="#d2cd57c8-de4b-11e6-a64f-02ba7def0216"/>
	</cim:TransformerWinding>
	<cim:ConnectivityNode rdf:ID="d2cef59c-de4b-11e6-a64f-02ba7def0216">
		<cim:IdentifiedObject.name>CN_111990696_110000</cim:IdentifiedObject.name>
	</cim:ConnectivityNode>
	<cim:Terminal rdf:ID="d2cef88a-de4b-11e6-a64f-02ba7def0216">
		<cim:Terminal.sequenceNumber>1</cim:Terminal.sequenceNumber>
		<cim:Terminal.ConductingEquipment rdf:resource="#d2cef2d6-de4b-11e6-a64f-02ba7def0216"/>
		<cim:Terminal.ConnectivityNode rdf:resource="#d2cef59c-de4b-11e6-a64f-02ba7def0216"/>
	</cim:Terminal>
	<cim:LoadResponseCharacteristic rdf:ID="d2cefb46-de4b-11e6-a64f-02ba7def0216">
		<cim:LoadResponseCharacteristic.pConstantPower>100000</cim:LoadResponseCharacteristic.pConstantPower>
	</cim:LoadResponseCharacteristic>
	<cim:EnergyConsumer rdf:ID="d2ceff7e-de4b-11e6-a64f-02ba7def0216">
		<cim:IdentifiedObject.name>L_111990696</cim:IdentifiedObject.name>
		<cim:ConductingEquipment.phases rdf:resource="http://iec.ch/TC57/2010/CIM-schema-cim15#PhaseCode.A"/>
		<cim:ConductingEquipment.BaseVoltage rdf:resource="#d2cc5b2a-de4b-11e6-a64f-02ba7def0216"/>
		<cim:EnergyConsumer.LoadResponse rdf:resource="#d2cefb46-de4b-11e6-a64f-02ba7def0216"/>
	</cim:EnergyConsumer>
	<cim:Terminal rdf:ID="d2cf029e-de4b-11e6-a64f-02ba7def0216">
		<cim:Terminal.sequenceNumber>1</cim:Terminal.sequenceNumber>
		<cim:Terminal.ConductingEquipment rdf:resource="#d2ceff7e-de4b-11e6-a64f-02ba7def0216"/>
		<cim:Terminal.ConnectivityNode rdf:resource="#d2cef59c-de4b-11e6-a64f-02ba7def0216"/>
	</cim:Terminal>
	<cim:TransformerWinding rdf:ID="d2cf06fe-de4b-11e6-a64f-02ba7def0216">
		<cim:IdentifiedObject.name>TW_370348954_110000</cim:IdentifiedObject.name>
		<cim:TransformerWinding.x>1.0</cim:TransformerWinding.x>
		<cim:TransformerWinding.ratedS>5000000</cim:TransformerWinding.ratedS>
		<cim:TransformerWinding.r>1.0</cim:TransformerWinding.r>
		<cim:TransformerWinding.ratedU>110000</cim:TransformerWinding.ratedU>
		<cim:TransformerWinding.connectionType rdf:resource="http://iec.ch/TC57/2010/CIM-schema-cim15#WindingConnection.Yn"/>
		<cim:TransformerWinding.windingType rdf:resource="http://iec.ch/TC57/2010/CIM-schema-cim15#WindingType.secondary"/>
		<cim:ConductingEquipment.BaseVoltage rdf:resource="#d2cc5b2a-de4b-11e6-a64f-02ba7def0216"/>
		<cim:TransformerWinding.PowerTransformer rdf:resource="#d2ce013c-de4b-11e6-a64f-02ba7def0216"/>
	</cim:TransformerWinding>
	<cim:ConnectivityNode rdf:ID="d2cf09ba-de4b-11e6-a64f-02ba7def0216">
		<cim:IdentifiedObject.name>CN_370348954_110000</cim:IdentifiedObject.name>
	</cim:ConnectivityNode>
	<cim:Terminal rdf:ID="d2cf0d98-de4b-11e6-a64f-02ba7def0216">
		<cim:Terminal.sequenceNumber>1</cim:Terminal.sequenceNumber>
		<cim:Terminal.ConductingEquipment rdf:resource="#d2cf06fe-de4b-11e6-a64f-02ba7def0216"/>
		<cim:Terminal.ConnectivityNode rdf:resource="#d2cf09ba-de4b-11e6-a64f-02ba7def0216"/>
	</cim:Terminal>
	<cim:LoadResponseCharacteristic rdf:ID="d2cf1054-de4b-11e6-a64f-02ba7def0216">
		<cim:LoadResponseCharacteristic.pConstantPower>100000</cim:LoadResponseCharacteristic.pConstantPower>
	</cim:LoadResponseCharacteristic>
	<cim:EnergyConsumer rdf:ID="d2cf1478-de4b-11e6-a64f-02ba7def0216">
		<cim:IdentifiedObject.name>L_370348954</cim:IdentifiedObject.name>
		<cim:ConductingEquipment.phases rdf:resource="http://iec.ch/TC57/2010/CIM-schema-cim15#PhaseCode.A"/>
		<cim:ConductingEquipment.BaseVoltage rdf:resource="#d2cc5b2a-de4b-11e6-a64f-02ba7def0216"/>
		<cim:EnergyConsumer.LoadResponse rdf:resource="#d2cf1054-de4b-11e6-a64f-02ba7def0216"/>
	</cim:EnergyConsumer>
	<cim:Terminal rdf:ID="d2cf1798-de4b-11e6-a64f-02ba7def0216">
		<cim:Terminal.sequenceNumber>1</cim:Terminal.sequenceNumber>
		<cim:Terminal.ConductingEquipment rdf:resource="#d2cf1478-de4b-11e6-a64f-02ba7def0216"/>
		<cim:Terminal.ConnectivityNode rdf:resource="#d2cf09ba-de4b-11e6-a64f-02ba7def0216"/>
	</cim:Terminal>
	<cim:TransformerWinding rdf:ID="d2cf1bf8-de4b-11e6-a64f-02ba7def0216">
		<cim:IdentifiedObject.name>TW_36903323_110000</cim:IdentifiedObject.name>
		<cim:TransformerWinding.x>1.0</cim:TransformerWinding.x>
		<cim:TransformerWinding.ratedS>5000000</cim:TransformerWinding.ratedS>
		<cim:TransformerWinding.r>1.0</cim:TransformerWinding.r>
		<cim:TransformerWinding.ratedU>110000</cim:TransformerWinding.ratedU>
		<cim:TransformerWinding.connectionType rdf:resource="http://iec.ch/TC57/2010/CIM-schema-cim15#WindingConnection.Yn"/>
		<cim:TransformerWinding.windingType rdf:resource="http://iec.ch/TC57/2010/CIM-schema-cim15#WindingType.secondary"/>
		<cim:ConductingEquipment.BaseVoltage rdf:resource="#d2cc5b2a-de4b-11e6-a64f-02ba7def0216"/>
		<cim:TransformerWinding.PowerTransformer rdf:resource="#d2ce5ec0-de4b-11e6-a64f-02ba7def0216"/>
	</cim:TransformerWinding>
	<cim:ConnectivityNode rdf:ID="d2cf1ebe-de4b-11e6-a64f-02ba7def0216">
		<cim:IdentifiedObject.name>CN_36903323_110000</cim:IdentifiedObject.name>
	</cim:ConnectivityNode>
	<cim:Terminal rdf:ID="d2cf21ac-de4b-11e6-a64f-02ba7def0216">
		<cim:Terminal.sequenceNumber>1</cim:Terminal.sequenceNumber>
		<cim:Terminal.ConductingEquipment rdf:resource="#d2cf1bf8-de4b-11e6-a64f-02ba7def0216"/>
		<cim:Terminal.ConnectivityNode rdf:resource="#d2cf1ebe-de4b-11e6-a64f-02ba7def0216"/>
	</cim:Terminal>
	<cim:LoadResponseCharacteristic rdf:ID="d2cf2454-de4b-11e6-a64f-02ba7def0216">
		<cim:LoadResponseCharacteristic.pConstantPower>100000</cim:LoadResponseCharacteristic.pConstantPower>
	</cim:LoadResponseCharacteristic>
	<cim:EnergyConsumer rdf:ID="d2cf286e-de4b-11e6-a64f-02ba7def0216">
		<cim:IdentifiedObject.name>L_36903323</cim:IdentifiedObject.name>
		<cim:ConductingEquipment.phases rdf:resource="http://iec.ch/TC57/2010/CIM-schema-cim15#PhaseCode.A"/>
		<cim:ConductingEquipment.BaseVoltage rdf:resource="#d2cc5b2a-de4b-11e6-a64f-02ba7def0216"/>
		<cim:EnergyConsumer.LoadResponse rdf:resource="#d2cf2454-de4b-11e6-a64f-02ba7def0216"/>
	</cim:EnergyConsumer>
	<cim:Terminal rdf:ID="d2cf2b8e-de4b-11e6-a64f-02ba7def0216">
		<cim:Terminal.sequenceNumber>1</cim:Terminal.sequenceNumber>
		<cim:Terminal.ConductingEquipment rdf:resource="#d2cf286e-de4b-11e6-a64f-02ba7def0216"/>
		<cim:Terminal.ConnectivityNode rdf:resource="#d2cf1ebe-de4b-11e6-a64f-02ba7def0216"/>
	</cim:Terminal>
</rdf:RDF>
